TestPipInstallProgram/__init__.py
TestPipInstallProgram/simple_calc.py
TestPipInstallProgram-0.0.2.dist-info/LICENSE
TestPipInstallProgram-0.0.2.dist-info/METADATA
TestPipInstallProgram-0.0.2.dist-info/WHEEL
TestPipInstallProgram-0.0.2.dist-info/top_level.txt
TestPipInstallProgram-0.0.2.dist-info/RECORD
