Metadata-Version: 2.2
Name: TestPipInstallProgram
Version: 0.0.2
Summary: Simple calculater
Home-page: https://github.com/OliverJansson/TestPipInstallProgram
Author: Oliver Jansson
Author-email: billy27000@gmail.com
Classifier: Development Status :: 1 - Planning
Classifier: License :: OSI Approved :: MIT License
Classifier: Operating System :: POSIX :: Linux
Classifier: Programming Language :: Python :: 3
Requires-Python: >=3.0
License-File: LICENSE
